{"data":{"allMarkdownRemark":{"edges":[{"node":{"frontmatter":{"type":"Monohull","name":"Sivir","path":"/sivir"},"excerpt":"Monohull BOiiiiiis"}},{"node":{"frontmatter":{"type":"Monohull","name":"Syndra","path":"/syndra"},"excerpt":"Monohull BOiiiiiis"}},{"node":{"frontmatter":{"type":"Monohull","name":"Keisha","path":"/Keisha"},"excerpt":"This is the second monohull boat on our page. ITS GROWING\n"}},{"node":{"frontmatter":{"type":"Monohull","name":"Nely","path":"/nelly"},"excerpt":"Monohull \n"}},{"node":{"frontmatter":{"type":"Monohull","name":"Sharkoid","path":"/sharkoid"},"excerpt":"Motorboat - one of the fastest"}},{"node":{"frontmatter":{"type":"Monohull","name":"Elisa","path":"/elisa"},"excerpt":"Monohull BOiiiiiis"}},{"node":{"frontmatter":{"type":"Monohull","name":"Larissa","path":"/Larissa"},"excerpt":"This is the first monohull boat on our page\n"}}]}},"pageContext":{}}